webpage_content_scraper/__init__.py
webpage_content_scraper-0.3.dist-info/LICENSE
webpage_content_scraper-0.3.dist-info/METADATA
webpage_content_scraper-0.3.dist-info/WHEEL
webpage_content_scraper-0.3.dist-info/top_level.txt
webpage_content_scraper-0.3.dist-info/RECORD
