Metadata-Version: 2.1
Name: webpage-content-scraper
Version: 0.3
Summary: Scrape only the content from a webpage using Firefox's reader view.
Author: Ryan Blunden
License: Apache-2.0
Project-URL: Homepage, https://github.com/ryan-blunden/python-webpage-content-scraper
Project-URL: Changelog, https://github.com/ryan-blunden/python-webpage-content-scraper/releases
Project-URL: Issues, https://github.com/ryan-blunden/python-webpage-content-scraper/issues
Project-URL: CI, https://github.com/ryan-blunden/python-webpage-content-scraper/actions
Classifier: License :: OSI Approved :: Apache Software License
Requires-Python: >=3.8
License-File: LICENSE
Requires-Dist: playwright
Requires-Dist: markdownify
Requires-Dist: beautifulsoup4
Provides-Extra: dev
Requires-Dist: symbex ; extra == 'dev'
Provides-Extra: test
Requires-Dist: pytest ; extra == 'test'
Requires-Dist: pytest-mock ; extra == 'test'
Requires-Dist: ruff ; extra == 'test'
Requires-Dist: mypy ; extra == 'test'
